rowgen/__init__.py
rowgen/extract_from_db.py
rowgen/hf_api.py
rowgen/main.py
rowgen/sql_parser.py
rowgen-0.2.1.dist-info/METADATA
rowgen-0.2.1.dist-info/WHEEL
rowgen-0.2.1.dist-info/entry_points.txt
rowgen-0.2.1.dist-info/RECORD
