Metadata-Version: 2.3
Name: rowgen
Version: 0.2.1
Summary: Generate and insert realistic context-aware ai generative data into databases
License: MIT
Author: ArsalanJdev
Author-email: arsalanjdev@gmail.com
Requires-Python: >=3.12
Classifier: Intended Audience :: Developers
Classifier: License :: OSI Approved :: MIT License
Classifier: Programming Language :: Python :: 3
Classifier: Programming Language :: Python :: 3.12
Requires-Dist: huggingface-hub (>=0.31.4,<0.32.0)
Requires-Dist: python-dotenv (>=1.1.0,<2.0.0)
Requires-Dist: sqlalchemy (>=2.0.41,<3.0.0)
Project-URL: Homepage, https://github.com/Arsalanjdev/RowGen
